gcloud_sync_ssh/__init__.py
gcloud_sync_ssh/__main__.py
gcloud_sync_ssh/cli.py
gcloud_sync_ssh/gcloud_auth.py
gcloud_sync_ssh/gcloud_config.py
gcloud_sync_ssh/gcloud_instances.py
gcloud_sync_ssh/gcloud_projects.py
gcloud_sync_ssh/host_config.py
gcloud_sync_ssh/ssh_config.py
gcloud_sync_ssh/util/__init__.py
gcloud_sync_ssh/util/case_insensitive_dict.py
gcloud_sync_ssh/util/cased_enum.py
gcloud_sync_ssh/util/cmd.py
gcloud_sync_ssh/util/color_diff.py
gcloud_sync_ssh/util/globbing.py
gcloud_sync_ssh-1.0.0b4.dist-info/LICENSE
gcloud_sync_ssh-1.0.0b4.dist-info/METADATA
gcloud_sync_ssh-1.0.0b4.dist-info/WHEEL
gcloud_sync_ssh-1.0.0b4.dist-info/entry_points.txt
gcloud_sync_ssh-1.0.0b4.dist-info/top_level.txt
gcloud_sync_ssh-1.0.0b4.dist-info/RECORD
