Metadata-Version: 2.1
Name: gcloud-sync-ssh
Version: 1.0.0b4
Summary: A tool to synchronize GCP instances IP addresses to SSH config.
Home-page: https://github.com/mrzor/gcloud_sync_ssh
Author: mrzor
License: MIT
Platform: UNKNOWN
Classifier: Programming Language :: Python :: 3
Classifier: License :: OSI Approved :: MIT License
Classifier: Operating System :: OS Independent
Classifier: Development Status :: 4 - Beta
Classifier: Environment :: Console
Classifier: Intended Audience :: Developers
Classifier: Intended Audience :: System Administrators
Classifier: Topic :: System :: Systems Administration
Requires-Python: >=3.6
Requires-Dist: click (>=7.1)
Requires-Dist: loguru (>=0.5)
Requires-Dist: ostruct (>=4.0)
Requires-Dist: pydantic (>=1.6)
Requires-Dist: colored (>=1.4.2)
